dreamlake/__init__.py
dreamlake/configurator.py
dreamlake/connection.py
dreamlake/executor.py
dreamlake/parser.py
dreamlake/query.py
dreamlake-1.1.2.dist-info/METADATA
dreamlake-1.1.2.dist-info/WHEEL
dreamlake-1.1.2.dist-info/top_level.txt
dreamlake-1.1.2.dist-info/RECORD
